envvault/__init__.py
envvault/cli.py
envvault/core.py
envvault/settings.py
envvault-0.1.7.dist-info/METADATA
envvault-0.1.7.dist-info/WHEEL
envvault-0.1.7.dist-info/entry_points.txt
envvault-0.1.7.dist-info/RECORD
