Metadata-Version: 2.3
Name: envvault
Version: 0.1.7
Summary: A tool to manage encrypted environment variables.
License: MIT
Author: jin
Author-email: jin.xiaoming@ekohe.com
Requires-Python: >3.9.1,<4.0
Classifier: License :: OSI Approved :: MIT License
Classifier: Programming Language :: Python :: 3
Classifier: Programming Language :: Python :: 3.10
Classifier: Programming Language :: Python :: 3.11
Classifier: Programming Language :: Python :: 3.12
Classifier: Programming Language :: Python :: 3.13
Requires-Dist: click (>=8.1.8,<9.0.0)
Requires-Dist: cryptography (>=44.0.0,<45.0.0)
Requires-Dist: lru-cache (>=0.2.3,<0.3.0)
Requires-Dist: pydantic (>=2.10.5,<3.0.0)
Requires-Dist: pydantic-settings (>=2.7.1,<3.0.0)
Requires-Dist: python-dotenv (>=1.0.1,<2.0.0)
